newberryai/EDI.py
newberryai/ExcelO.py
newberryai/MedicalClaimVerifier.py
newberryai/Medical_coding.py
newberryai/PII_extractor.py
newberryai/PII_masking.py
newberryai/__init__.py
newberryai/_version.py
newberryai/agent.py
newberryai/cli.py
newberryai/ddx.py
newberryai/debugger.py
newberryai/eda.py
newberryai/face_detection.py
newberryai/face_recognigation.py
newberryai/features_gpt5.py
newberryai/function_registry.py
newberryai/gpt_agent.py
newberryai/handwritten2text.py
newberryai/health_chat.py
newberryai/health_compliance.py
newberryai/healthscribe.py
newberryai/image_generator.py
newberryai/img_search.py
newberryai/medical_bill_extractor.py
newberryai/nl2sql.py
newberryai/pdf_extraction.py
newberryai/pdf_summarizer.py
newberryai/speechtospeech.py
newberryai/video_generator.py
newberryai/virtual_tryon.py
newberryai-0.2.4.dist-info/licenses/LICENSE
newberryai-0.2.4.dist-info/METADATA
newberryai-0.2.4.dist-info/WHEEL
newberryai-0.2.4.dist-info/entry_points.txt
newberryai-0.2.4.dist-info/top_level.txt
newberryai-0.2.4.dist-info/RECORD
