Metadata-Version: 2.4
Name: newberryai
Version: 0.2.4
Summary: NewberryAI Python Package
Home-page: https://github.com/HolboxAI/newberryai
Author: Saurabh Patil, Jaideepsinh Dabhi, Harsh Langaliya , Harshika Agarwal , Satyanarayan Sahoo , Maya Chitor , Mira Chitor, Ramesh Chitor
Author-email: jaideep@newberry.ai
License: MIT
Classifier: License :: OSI Approved :: MIT License
Classifier: Programming Language :: Python :: 3
Classifier: Operating System :: OS Independent
Requires-Python: >=3.6
License-File: LICENSE
Requires-Dist: boto3
Requires-Dist: requests
Requires-Dist: pytest
Requires-Dist: opencv-python
Requires-Dist: setuptools
Requires-Dist: gradio
Requires-Dist: numpy
Requires-Dist: pyaudio
Requires-Dist: sounddevice
Requires-Dist: pydub
Requires-Dist: textual
Requires-Dist: openai[realtime]
Requires-Dist: typing_extensions
Requires-Dist: PyMuPDF
Requires-Dist: pandas
Requires-Dist: matplotlib
Requires-Dist: seaborn
Requires-Dist: python-dotenv
Requires-Dist: mysql-connector-python
Requires-Dist: Pillow
Requires-Dist: faiss-cpu
Dynamic: author
Dynamic: author-email
Dynamic: classifier
Dynamic: description
Dynamic: description-content-type
Dynamic: home-page
Dynamic: license
Dynamic: license-file
Dynamic: requires-dist
Dynamic: requires-python
Dynamic: summary
